metabypass/__init__.py
metabypass/main.py
metabypass-0.1.6.dist-info/METADATA
metabypass-0.1.6.dist-info/WHEEL
metabypass-0.1.6.dist-info/top_level.txt
metabypass-0.1.6.dist-info/RECORD
